{
    "ticker": "MSFT",
    "company_name": "Microsoft Corporation",
    "overall_score": 85.6,
    "scores": {
        "revenue_growth": {
            "score": 71.1,
            "explanation": "MSFT generated a revenue CAGR of 12.4% over the available period. This is considered strong long-term revenue growth, resulting in a score of 71.1/100."
        },
        "financial_strength": {
            "score": 100,
            "explanation": "MSFT has an interest coverage ratio of 53.9x. The company easily covers its interest obligations, indicating excellent financial strength. Positive free cash flow increased the score."
        }
    }
}